md_rbrb.py
md_rbrb-1.1.1.data/data/share/doc/md_rbrb/LICENSE
md_rbrb-1.1.1.data/data/share/doc/md_rbrb/README.md
md_rbrb-1.1.1.data/data/share/doc/md_rbrb/README.rst
md_rbrb-1.1.1.dist-info/DESCRIPTION.rst
md_rbrb-1.1.1.dist-info/METADATA
md_rbrb-1.1.1.dist-info/RECORD
md_rbrb-1.1.1.dist-info/WHEEL
md_rbrb-1.1.1.dist-info/entry_points.txt
md_rbrb-1.1.1.dist-info/metadata.json
md_rbrb-1.1.1.dist-info/top_level.txt
